recall/__init__.py
recall/constants.py
recall/withrecall.py
recall/extraction/extractor.py
recall/extraction/strategies.py
recall/handlers/user_message_handler.py
recall/llm/extractor.py
recall/llm/llm_client.py
recall/llm/prompt_serializer.py
recall/memory/memory_entry.py
recall/memory/memory_store.py
recall_sdk-0.2.0.dist-info/METADATA
recall_sdk-0.2.0.dist-info/WHEEL
recall_sdk-0.2.0.dist-info/top_level.txt
recall_sdk-0.2.0.dist-info/RECORD
