Metadata-Version: 2.4
Name: recall-sdk
Version: 0.2.0
Summary: A pluggable memory layer for LLM apps
Author-email: Mrigank Khandelwal <khandelwal.mr@northeastern.edu>
License: MIT
Project-URL: Homepage, https://github.com/Mrigankkh/recall
Requires-Python: >=3.8
Requires-Dist: openai>=1.0.0
Requires-Dist: numpy
Requires-Dist: python-dotenv
